  <ShipClassDetail>
    <Name>Constitution Class</Name>
    <Id>constitution_class</Id>
    <Maneuvers>

    </Maneuvers>
    <FrontArc>180</FrontArc>
    <RearArc></RearArc>
  </ShipClassDetail>
  <ShipClassDetail>
    <Name>Constitution Class</Name>
    <Id>constitution_class</Id>
    <Maneuvers>

    </Maneuvers>
    <FrontArc>180</FrontArc>
    <RearArc></RearArc>
  </ShipClassDetail>
  <ShipClassDetail>
    <Name>Xindi Reptilian Warship</Name>
    <Id>xindi_reptilian_warship</Id>
    <Maneuvers>

    </Maneuvers>
    <FrontArc>90</FrontArc>
    <RearArc></RearArc>
  </ShipClassDetail>
  <ShipClassDetail>
    <Name>Xindi Reptilian Warship</Name>
    <Id>xindi_reptilian_warship</Id>
    <Maneuvers>

    </Maneuvers>
    <FrontArc>90</FrontArc>
    <RearArc></RearArc>
  </ShipClassDetail>
  <ShipClassDetail>
    <Name>Delta Flyer Class Shuttlecraft</Name>
    <Id>delta_flyer_class_shuttlecraft</Id>
    <Maneuvers>

    </Maneuvers>
    <FrontArc>90</FrontArc>
    <RearArc>90</RearArc>
  </ShipClassDetail>
  <ShipClassDetail>
    <Name>Delta Flyer Class Shuttlecraft</Name>
    <Id>delta_flyer_class_shuttlecraft</Id>
    <Maneuvers>

    </Maneuvers>
    <FrontArc>90</FrontArc>
    <RearArc>90</RearArc>
  </ShipClassDetail>
